my_own_package/__init__.py
Frunza_firsti_package-0.3.0.dist-info/METADATA
Frunza_firsti_package-0.3.0.dist-info/WHEEL
Frunza_firsti_package-0.3.0.dist-info/top_level.txt
Frunza_firsti_package-0.3.0.dist-info/RECORD
