Metadata-Version: 2.1
Name: Frunza-firsti-package
Version: 0.3.0
Summary: This is my first packages
Author: Cosofret Bogdan
Author-email: cosofret.bogdan@yahoo.com
